{
  "date": "September 9th, 2021",
  "title": "DeCaLiBro-n Adventure",
  "termini": "Kite Lake to Mount DeCaLiBron",
  "location": "Mosquito Range",
  "image": "2021/09/09/8e1e0c1f-c391-4bc0-807c-7bdd8d20815b.jpeg",
  "excerpt": "The DeCaLiBro-n route connected three 14,000-foot peaks in a single day, offering sweeping views and thrilling ridges. Completing Democrat, Cameron, and Lincoln left us exhausted but exhilarated, a true alpine adventure.",
  "gain": "3134",
  "loss": "1741",
  "miles": "11.52",
  "minutes": "402",
  "tooltips": ["right", "top"]
}
