{
  "date": [
    "7/24/2024",
    "7/25/2024"
  ],
  "timestamp": "1721772000",
  "id": "geneva-switzerland-2024",
  "title": "Geneva",
  "location": "Switzerland",
  "category": "cities",
  "coordinates": "46.204391° N, 6.143158° E",
  "tags": [
    "cityscape",
    "monuments",
    "europe",
    "switzerland",
    "destination"
  ],
  "images": [
    {
      "src": "2024/07/24/f6f7470b-5e4e-42f7-aa59-ccabe81778bf.jpeg",
      "title": "Jet d'Eau",
      "location": "Geneva",
      "date": "07/24/2024",
      "exif": {
        "aperture": "1/1699",
        "camera": "iPhone 13 Pro",
        "exposure": "0.0",
        "fnumber": "1.50",
        "focal": 26,
        "iso": 50
      }
    },
    {
      "src": "2024/07/24/e19b87b3-ff48-499f-a225-3d4d608e9311.jpeg",
      "title": "Cathedral attic",
      "location": "Geneva",
      "date": "07/24/2024",
      "exif": {
        "aperture": "1/1699",
        "camera": "iPhone 13 Pro",
        "exposure": "0.0",
        "fnumber": "1.50",
        "focal": 26,
        "iso": 800
      }
    },
    {
      "src": "2024/07/24/e38ad9d4-d8b7-433c-bdec-55294d442928.jpeg",
      "title": "Botanical Oasis",
      "location": "Geneva",
      "date": "07/25/2024",
      "exif": {
        "aperture": "1/6960",
        "camera": "iPhone 13 Pro",
        "exposure": "0.0",
        "fnumber": "1.80",
        "focal": 13,
        "iso": 32
      }
    }
  ]
}