{
  "date": [
    "03/14/2026",
    "03/15/2026"
  ],
  "timestamp": "1773554400",
  "id": "river-ridge-trail-2026",
  "title": "River Ridge Trail 2026",
  "location": "Westville, Illinois, USA",
  "category": "backpacking",
  "coordinates": "40.007973° N, 87.571681° W",
  "tags": [
    "landscape",
    "trail",
    "north america",
    "weekend hike",
    "backpacking"
  ],
  "images": [
    {
      "src": "2026/03/14/8e8fd062-270f-4081-96c3-ee072a81caab.jpeg",
      "title": "Blaze",
      "location": "Forest Glen Preserve",
      "date": "03/15/2026",
      "exif": {
        "aperture": "2/2750",
        "camera": "iPhone 16 Pro",
        "exposure": "0.0",
        "fnumber": "2.20",
        "focal": 14,
        "iso": 16
      }
    },
    {
      "src": "2026/03/14/0048f3c5-e902-4713-8745-5562d51566a7.jpeg",
      "title": "Through the trees",
      "location": "Forest Glen Preserve",
      "date": "03/14/2026",
      "exif": {
        "aperture": "2/2750",
        "camera": "iPhone 16 Pro",
        "exposure": "0.0",
        "fnumber": "2.20",
        "focal": 14,
        "iso": 32
      }
    },
    {
      "src": "2026/03/14/2665b912-007f-485f-b636-07079e321e20.jpeg",
      "title": "Gravel path",
      "location": "Forest Glen Preserve",
      "date": "03/14/2026",
      "exif": {
        "aperture": "1/6638",
        "camera": "iPhone 16 Pro",
        "exposure": "0.0",
        "fnumber": "1.78",
        "focal": 24,
        "iso": 64
      }
    },
    {
      "src": "2026/03/14/1e1be596-c236-4cee-9eb2-fac89329e0e6.jpeg",
      "title": "Golden grasses",
      "location": "Forest Glen Preserve",
      "date": "03/15/2026",
      "exif": {
        "aperture": "1/6638",
        "camera": "iPhone 16 Pro",
        "exposure": "0.0",
        "fnumber": "1.78",
        "focal": 24,
        "iso": 64
      }
    },
    {
      "src": "2026/03/14/bfb02a8a-045d-456f-a389-95aefbff4628.jpeg",
      "title": "Fallen tree",
      "location": "Forest Glen Preserve",
      "date": "03/15/2026",
      "exif": {
        "aperture": "1/6638",
        "camera": "iPhone 16 Pro",
        "exposure": "0.0",
        "fnumber": "1.78",
        "focal": 24,
        "iso": 100
      }
    }
  ]
}